codie.py
codie-0.0.5.dist-info/LICENSE
codie-0.0.5.dist-info/METADATA
codie-0.0.5.dist-info/WHEEL
codie-0.0.5.dist-info/top_level.txt
codie-0.0.5.dist-info/RECORD
