Metadata-Version: 2.1
Name: codie
Version: 0.0.5
Summary: codie geometry library for Python
Author: Danil Nagy
Classifier: Programming Language :: Python :: 3
Classifier: License :: OSI Approved :: MIT License
Classifier: Operating System :: OS Independent
Requires-Python: >=3.6
License-File: LICENSE
Requires-Dist: rhino3dm
Requires-Dist: Shapely
